valladopy/__init__.py
valladopy/constants.py
valladopy/astro/__init__.py
valladopy/astro/celestial/__init__.py
valladopy/astro/celestial/jpl.py
valladopy/astro/celestial/moon.py
valladopy/astro/celestial/sun.py
valladopy/astro/celestial/utils.py
valladopy/astro/iod/__init__.py
valladopy/astro/iod/angles.py
valladopy/astro/iod/lambert.py
valladopy/astro/iod/utils.py
valladopy/astro/maneuver/__init__.py
valladopy/astro/maneuver/transfer.py
valladopy/astro/maneuver/utils.py
valladopy/astro/mission/__init__.py
valladopy/astro/mission/geometry.py
valladopy/astro/od/__init__.py
valladopy/astro/od/diffcorrection.py
valladopy/astro/od/utils.py
valladopy/astro/perturbations/__init__.py
valladopy/astro/perturbations/gravity.py
valladopy/astro/perturbations/utils.py
valladopy/astro/sgp4/__init__.py
valladopy/astro/sgp4/deep_space.py
valladopy/astro/sgp4/sgp4.py
valladopy/astro/sgp4/utils.py
valladopy/astro/time/__init__.py
valladopy/astro/time/data.py
valladopy/astro/time/fk4.py
valladopy/astro/time/frame_conversions.py
valladopy/astro/time/iau_transform.py
valladopy/astro/time/sidereal.py
valladopy/astro/time/utils.py
valladopy/astro/twobody/__init__.py
valladopy/astro/twobody/frame_conversions.py
valladopy/astro/twobody/hills.py
valladopy/astro/twobody/kepler.py
valladopy/astro/twobody/newton.py
valladopy/astro/twobody/utils.py
valladopy/astro/twobody/covariance/__init__.py
valladopy/astro/twobody/covariance/frame_conversions.py
valladopy/astro/twobody/covariance/utils.py
valladopy/mathtime/__init__.py
valladopy/mathtime/calendar.py
valladopy/mathtime/julian_date.py
valladopy/mathtime/rotations.py
valladopy/mathtime/utils.py
valladopy/mathtime/vector.py
valladopy-0.4.1.dist-info/METADATA
valladopy-0.4.1.dist-info/WHEEL
valladopy-0.4.1.dist-info/top_level.txt
valladopy-0.4.1.dist-info/RECORD
