Metadata-Version: 2.4
Name: valladopy
Version: 0.4.1
Summary: Routines from Fundamentals of Astrodynamics and Applications by David Vallado
Author-email: David Vallado <davallado@gmail.com>
License: AGPL-3.0
Requires-Dist: numpy==1.26.4
Requires-Dist: pydantic==2.9.2
Requires-Dist: scipy==1.13.1
